igorwriter/__init__.py
igorwriter/builtin_names.py
igorwriter/errors.py
igorwriter/igorwave.py
igorwriter/utils.py
igorwriter/validator.py
igorwriter/builtins/functions.txt
igorwriter/builtins/keywords.txt
igorwriter/builtins/operations.txt
igorwriter-0.7.0.dist-info/LICENSE.txt
igorwriter-0.7.0.dist-info/METADATA
igorwriter-0.7.0.dist-info/WHEEL
igorwriter-0.7.0.dist-info/top_level.txt
igorwriter-0.7.0.dist-info/RECORD
