Metadata-Version: 2.1
Name: igorwriter
Version: 0.7.0
Summary: Write IGOR binary (.ibw) or text (.itx) files from numpy array
Home-page: https://github.com/t-onoz/igorwriter
Author: t-onoz
License: MIT
Classifier: Development Status :: 3 - Alpha
Classifier: License :: OSI Approved :: MIT License
Classifier: Programming Language :: Python :: 3
License-File: LICENSE.txt
Requires-Dist: numpy
